somewhere/__init__.py
somewhere/main.py
somewhere/where.py
somewhere/which.py
somewhere-0.0.1.dist-info/DESCRIPTION.rst
somewhere-0.0.1.dist-info/METADATA
somewhere-0.0.1.dist-info/RECORD
somewhere-0.0.1.dist-info/WHEEL
somewhere-0.0.1.dist-info/entry_points.txt
somewhere-0.0.1.dist-info/metadata.json
somewhere-0.0.1.dist-info/top_level.txt
